nvertake/__init__.py
nvertake/cli.py
nvertake/memory.py
nvertake/scheduler.py
nvertake/utils.py
nvertake-0.1.0.dist-info/licenses/LICENSE
nvertake-0.1.0.dist-info/METADATA
nvertake-0.1.0.dist-info/WHEEL
nvertake-0.1.0.dist-info/entry_points.txt
nvertake-0.1.0.dist-info/top_level.txt
nvertake-0.1.0.dist-info/RECORD
