Metadata-Version: 2.4
Name: nvertake
Version: 0.1.0
Summary: A Python package for preemptive scheduling on NVIDIA GPUs
Author: L1ght
License: MIT
Project-URL: Homepage, https://github.com/FanBB2333/nVertake
Project-URL: Repository, https://github.com/FanBB2333/nVertake
Keywords: nvidia,gpu,cuda,scheduling,priority
Classifier: Development Status :: 3 - Alpha
Classifier: Intended Audience :: Developers
Classifier: License :: OSI Approved :: MIT License
Classifier: Programming Language :: Python :: 3
Classifier: Programming Language :: Python :: 3.8
Classifier: Programming Language :: Python :: 3.9
Classifier: Programming Language :: Python :: 3.10
Classifier: Programming Language :: Python :: 3.11
Classifier: Programming Language :: Python :: 3.12
Classifier: Topic :: System :: Hardware
Classifier: Topic :: Scientific/Engineering :: Artificial Intelligence
Requires-Python: >=3.8
License-File: LICENSE
Requires-Dist: torch
Requires-Dist: psutil
Provides-Extra: dev
Requires-Dist: pytest; extra == "dev"
Dynamic: license-file
